stellarmortis/__init__.py
stellarmortis/galaxy.py
stellarmortis/kick.py
stellarmortis/mass.py
stellarmortis/underworld.py
stellarmortis/utils.py
stellarmortis/microlensing/__init__.py
stellarmortis/microlensing/plot.py
stellarmortis/microlensing/simulate.py
stellarmortis-0.0.9.dist-info/METADATA
stellarmortis-0.0.9.dist-info/WHEEL
stellarmortis-0.0.9.dist-info/top_level.txt
stellarmortis-0.0.9.dist-info/RECORD
